ocfl_rehydration/__init__.py
ocfl_rehydration/drs_descriptor.py
ocfl_rehydration/drs_file.py
ocfl_rehydration/main.py
ocfl_rehydration/ocfl_inventory.py
ocfl_rehydration/rehydrator.py
ocfl_rehydration-1.1.1.dist-info/LICENSE
ocfl_rehydration-1.1.1.dist-info/METADATA
ocfl_rehydration-1.1.1.dist-info/WHEEL
ocfl_rehydration-1.1.1.dist-info/top_level.txt
ocfl_rehydration-1.1.1.dist-info/RECORD
