Metadata-Version: 2.1
Name: ocfl_rehydration
Version: 1.1.1
Summary: Utility for reconstituting OCFL objects
Home-page: https://github.com/harvard-lts/ocfl_rehydration
Author: Andrew Woods
Author-email: Andrew Woods <awoods01@gmail.com>
License:                                  Apache License
Project-URL: Homepage, https://github.com/harvard-lts/ocfl_rehydration
Classifier: License :: OSI Approved :: Apache Software License
Classifier: Programming Language :: Python
Classifier: Programming Language :: Python :: 3
Requires-Python: >=3.9
License-File: LICENSE
Requires-Dist: lxml>=4.9.3
Requires-Dist: project-paths>=1.1.1
Requires-Dist: pytest>=7.4.2
